fireplan/__init__.py
fireplan/fireplan.py
fireplan/models.py
python_fireplan-0.3.2.dist-info/licenses/LICENSE
python_fireplan-0.3.2.dist-info/METADATA
python_fireplan-0.3.2.dist-info/WHEEL
python_fireplan-0.3.2.dist-info/top_level.txt
python_fireplan-0.3.2.dist-info/RECORD
