Metadata-Version: 2.4
Name: python-fireplan
Version: 0.3.2
Summary: A python package for the public fireplan API.
Author-email: bouni <bouni-github@owee.de>
Project-URL: Homepage, https://github.com/Bouni/python-fireplan
Project-URL: Repository, https://github.com/Bouni/python-fireplan.git
Project-URL: Issues, https://github.com/Bouni/python-fireplan/issues
Requires-Python: >=3.12
License-File: LICENSE
Requires-Dist: pydantic>=2.9.2
Requires-Dist: requests>=2.32.3
Dynamic: license-file
